[
    {
        "id":1,
        "Catg":"Handicrafts .Asha Foundation",
        "Name":"Woven Jute Tote Bag",
        "url":"./../src/assets/Category/img1.png",
        "price":"$24.00",
        "prv_price":"4.8",
        "tagline":"WOMEN'S COLLECTIVE",
        "quantity":"1kg Pack",
        "color":"#31e87a",
        "off":"Best Seller"
        
    },
     {
        "id":2,
        "Catg":"Fruites",
        "Name":"Organic Red Apples",
        "url":"./../src/assets/Category/img2.png",
        "price":"₹ 650",
        "prv_price":"₹800",
        "tagline":"best seller",
        "quantity":"1kg Pack",
        "color":"#31e87a",
        "off":"Best Seller"
        
    },
     {
        "id":3,
        "Catg":"Fruites",
        "Name":"Organic Red Apples",
        "url":"./../src/assets/Category/img3.png",
        "price":"₹ 650",
        "prv_price":"₹800",
        "tagline":"best seller",
        "quantity":"1kg Pack",
        "color":"#31e87a",
        "off":"Best Seller"
        
    }
    ,
     {
        "id":4,
        "Catg":"Fruites",
        "Name":"Organic Red Apples",
        "url":"./../src/assets/Category/img4.png",
        "price":"₹ 650",
        "prv_price":"₹800",
        "tagline":"best seller",
        "quantity":"1kg Pack",
        "color":"#31e87a",
        "off":"Best Seller"
        
    },
    {
        "id":5,
        "Catg":"Fruites",
        "Name":"Organic Red Apples",
        "url":"./../src/assets/Category/img1.png",
        "price":"₹ 650",
        "prv_price":"₹800",
        "tagline":"best seller",
        "quantity":"1kg Pack",
        "color":"#31e87a",
        "off":"Best Seller"
        
    },
    {
        "id":6,
        "Catg":"Fruites",
        "Name":"Organic Red Apples",
        "url":"./../src/assets/Category/img1.png",
        "price":"₹ 650",
        "prv_price":"₹800",
        "color":"#31e87a",
        "off":"Best Seller"
        
    }
    ,{
        "id":7,
        "Catg":"Fruites",
        "Name":"Organic Red Apples",
        "url":"./../src/assets/Category/img1.png",
        "price":"₹ 650",
        "prv_price":"₹800",
        "tagline":"best seller",
        "quantity":"1kg Pack",
        "color":"#31e87a",
        "off":"Best Seller"
        
    }

    
    
]